{
    "crawls": [
        {
            "source": "NewYorkTimes",
            "type": "时政",
            "url": "https://cn.nytimes.com/"
        },
        {
            "source": "福布斯中文",
            "type": "财经",
            "url": "https://www.forbeschina.com/"
        },
        {
            "source": "经济观察网",
            "type": "财经",
            "url": "https://www.eeo.com.cn/"
        },
        {
            "source": "财富中文",
            "type": "财经",
            "url": "https://www.fortunechina.com/"
        },
        {
            "source": "联合早报-国际",
            "type": "时政",
            "url": "https://www.zaobao.com.sg/global"
        },
        {
            "source": "BBC",
            "type": "时政",
            "url": "https://www.bbc.com/"
        },
        {
            "source": "联合早报-中文",
            "type": "时政",
            "url": "https://www.zaobao.com.sg/cn"
        },
        {
            "source": "CNN",
            "type": "时政",
            "url": "https://edition.cnn.com/"
        },
        {
            "source": "新浪新闻",
            "type": "时政",
            "url": "https://news.sina.com.cn/"
        },
        {
            "source": "量子位-智能车",
            "type": "智驾",
            "url": "https://www.qbitai.com/category/auto"
        },
        {
            "source": "量子位-资讯",
            "type": "科技",
            "url": "https://www.qbitai.com/category/%e8%b5%84%e8%ae%af"
        },
        {
            "source": "AINews",
            "type": "AI",
            "url": "https://www.artificialintelligence-news.com/"
        },
        {
            "source": "Developer Tech",
            "type": "科技",
            "url": "https://www.developer-tech.com/"
        },
        {
            "source": "Nvidia News",
            "type": "科技",
            "url": "https://www.nvidia.cn/newsroom/news/"
        },
        {
            "source": "雷锋网-智能驾驶",
            "type": "智驾",
            "url": "https://www.leiphone.com/category/transportation"
        },
        {
            "source": "东方财富网",
            "type": "财经",
            "url": "https://www.eastmoney.com/default.html"
        }
    ],
    "storage": {
        "host": "localhost",
        "port": 3306,
        "username": "root",
        "password": "lym123",
        "database": "open_eyes_test"
    },
    "mode":"prod"
}